prism_pruner/__init__.py
prism_pruner/algebra.py
prism_pruner/conformer_ensemble.py
prism_pruner/graph_manipulations.py
prism_pruner/periodic_table.py
prism_pruner/pruner.py
prism_pruner/rmsd.py
prism_pruner/torsion_module.py
prism_pruner/typing.py
prism_pruner/utils.py
prism_pruner-0.0.7.dist-info/licenses/LICENSE
prism_pruner-0.0.7.dist-info/METADATA
prism_pruner-0.0.7.dist-info/WHEEL
prism_pruner-0.0.7.dist-info/top_level.txt
prism_pruner-0.0.7.dist-info/RECORD
