Metadata-Version: 2.4
Name: prism_pruner
Version: 0.0.7
Summary: Prism Pruner
Author-email: Nicolò Tampellini <nicolo.tampellini@yale.edu>
License-Expression: MIT
Requires-Python: >=3.12
License-File: LICENSE
Requires-Dist: networkx>=3.0
Requires-Dist: numpy>=2.0
Requires-Dist: scipy>=1.10
Requires-Dist: tqdm>=4
Dynamic: license-file
